papermill_watermark/__init__.py
papermill_watermark/engine.py
papermill_watermark-0.1.0.dist-info/LICENSE
papermill_watermark-0.1.0.dist-info/METADATA
papermill_watermark-0.1.0.dist-info/WHEEL
papermill_watermark-0.1.0.dist-info/entry_points.txt
papermill_watermark-0.1.0.dist-info/RECORD
